helicon/sequenceai/__init__.py
helicon/sequenceai/predictor.py
helicon_sequenceai-0.1.0.dist-info/METADATA
helicon_sequenceai-0.1.0.dist-info/WHEEL
helicon_sequenceai-0.1.0.dist-info/licenses/LICENSE
helicon_sequenceai-0.1.0.dist-info/licenses/NOTICE
helicon_sequenceai-0.1.0.dist-info/RECORD
