Metadata-Version: 2.4
Name: helicon-sequenceai
Version: 0.1.0
Summary: Lightweight ONNX Runtime predictor for Helicon SequenceAI models.
Project-URL: Repository, https://github.com/heliconhq/helicon-sequenceai
Project-URL: Issues, https://github.com/heliconhq/helicon-sequenceai/issues
Author-email: Helicon <fraz.ali@helicon.ai>
License: Copyright (c) 2025 Helicon Technologies AB
License-File: LICENSE
License-File: NOTICE
Classifier: License :: OSI Approved :: Apache Software License
Classifier: Operating System :: OS Independent
Classifier: Programming Language :: Python :: 3 :: Only
Classifier: Programming Language :: Python :: 3.11
Classifier: Programming Language :: Python :: 3.12
Requires-Python: >=3.11
Requires-Dist: numpy>=2.0.0
Requires-Dist: onnxruntime>=1.22.0
Provides-Extra: gpu
Requires-Dist: onnxruntime-gpu>=1.22.0; (platform_system == 'Linux' and platform_machine == 'x86_64') and extra == 'gpu'
